[
{"name": "Lily", "raiting": 4.5, "reviews": 291, "buisness_page": "https://www.yelp.com/biz/lily-san-francisco", "Business_website": "https://www.lilyonclement.com"},
{"name": "Beit Rima", "raiting": 4.5, "reviews": 212, "buisness_page": "https://www.yelp.com/biz/beit-rima-san-francisco-4", "Business_website": "http://beitrimasf.com"},
{"name": "KAIY\u014c Rooftop", "raiting": 4.0, "reviews": 391, "buisness_page": "https://www.yelp.com/biz/kaiy%C5%8D-rooftop-san-francisco-5", "Business_website": "https://kaiyosf.com/kaiyorooft\u2026"},
{"name": "Marufuku Ramen", "raiting": 4.5, "reviews": 4242, "buisness_page": "https://www.yelp.com/biz/marufuku-ramen-san-francisco-5", "Business_website": "http://marufukuramen.com"},
{"name": "Savor", "raiting": 5.0, "reviews": 77, "buisness_page": "https://www.yelp.com/biz/savor-san-francisco-7", "Business_website": "https://savor.menu"},
{"name": "Dumpling House", "raiting": 4.5, "reviews": 382, "buisness_page": "https://www.yelp.com/biz/dumpling-house-san-francisco", "Business_website": "http://dumplinghouse.us"},
{"name": "Starbelly", "raiting": 4.0, "reviews": 2140, "buisness_page": "https://www.yelp.com/biz/starbelly-san-francisco", "Business_website": "http://www.starbellysf.com"},
{"name": "Bottega", "raiting": 4.5, "reviews": 459, "buisness_page": "https://www.yelp.com/biz/bottega-san-francisco-2", "Business_website": "https://www.bottegavalencia.co\u2026"},
{"name": "Loquat", "raiting": 4.5, "reviews": 31, "buisness_page": "https://www.yelp.com/biz/loquat-san-francisco", "Business_website": "http://www.loquatsf.com"},
{"name": "Jamie's Place", "raiting": 4.5, "reviews": 255, "buisness_page": "https://www.yelp.com/biz/jamies-place-san-francisco", "Business_website": "Get Directions"},
{"name": "Sotto Mare", "raiting": 4.5, "reviews": 4690, "buisness_page": "https://www.yelp.com/biz/sotto-mare-san-francisco-4", "Business_website": "http://www.sottomaresf.com/"},
{"name": "The Snug", "raiting": 4.0, "reviews": 352, "buisness_page": "https://www.yelp.com/biz/the-snug-san-francisco", "Business_website": "http://www.thesnugsf.com"},
{"name": "Dumpling Kitchen", "raiting": 4.5, "reviews": 49, "buisness_page": "https://www.yelp.com/biz/dumpling-kitchen-san-francisco-5", "Business_website": "http://www.dumplingkitchenca.c\u2026"},
{"name": "Fog Harbor Fish House", "raiting": 4.5, "reviews": 8580, "buisness_page": "https://www.yelp.com/biz/fog-harbor-fish-house-san-francisco-2", "Business_website": "https://fogharbor.com"},
{"name": "Fable", "raiting": 4.0, "reviews": 745, "buisness_page": "https://www.yelp.com/biz/fable-san-francisco", "Business_website": "http://www.fablesf.com/"},
{"name": "Purple Rice", "raiting": 4.5, "reviews": 229, "buisness_page": "https://www.yelp.com/biz/purple-rice-san-francisco", "Business_website": "Get Directions"},
{"name": "Zajang Grill", "raiting": 4.5, "reviews": 25, "buisness_page": "https://www.yelp.com/biz/zajang-grill-san-francisco", "Business_website": "https://www.zajanggrill.com"},
{"name": "BoBop", "raiting": 4.5, "reviews": 13, "buisness_page": "https://www.yelp.com/biz/bobop-san-francisco", "Business_website": "Get Directions"},
{"name": "Damansara", "raiting": 3.5, "reviews": 34, "buisness_page": "https://www.yelp.com/biz/damansara-san-francisco-7", "Business_website": "http://damansarasf.com"},
{"name": "Dumpling Home", "raiting": 4.5, "reviews": 736, "buisness_page": "https://www.yelp.com/biz/dumpling-home-san-francisco", "Business_website": "http://dumplinghome.com"},
{"name": "Um Ma", "raiting": 4.0, "reviews": 594, "buisness_page": "https://www.yelp.com/biz/um-ma-san-francisco-3", "Business_website": "http://www.ummasf.com"},
{"name": "Kitchen Story", "raiting": 4.0, "reviews": 3875, "buisness_page": "https://www.yelp.com/biz/kitchen-story-san-francisco", "Business_website": "http://kitchenstorysf.com"},
{"name": "Pearl", "raiting": 4.5, "reviews": 395, "buisness_page": "https://www.yelp.com/biz/pearl-6101-san-francisco-7", "Business_website": "http://www.pearl-sf.com"},
{"name": "The Tailor's Son", "raiting": 4.0, "reviews": 341, "buisness_page": "https://www.yelp.com/biz/the-tailors-son-san-francisco", "Business_website": "http://www.thetailorssonsf.com"},
{"name": "Limoncello", "raiting": 5.0, "reviews": 1531, "buisness_page": "https://www.yelp.com/biz/limoncello-san-francisco", "Business_website": "http://www.limoncellostogo.com"},
{"name": "Automat", "raiting": 4.0, "reviews": 167, "buisness_page": "https://www.yelp.com/biz/automat-san-francisco-2", "Business_website": "http://automatsf.com"},
{"name": "Wooden Spoon", "raiting": 4.5, "reviews": 554, "buisness_page": "https://www.yelp.com/biz/wooden-spoon-san-francisco", "Business_website": "http://www.woodenspoonsf.com"},
{"name": "Salmon Bar", "raiting": 5.0, "reviews": 6, "buisness_page": "https://www.yelp.com/biz/salmon-bar-san-francisco-2", "Business_website": "https://salmonbarsf.com"},
{"name": "JIJIME", "raiting": 4.5, "reviews": 511, "buisness_page": "https://www.yelp.com/biz/jijime-san-francisco-8", "Business_website": "http://www.jijime.com"},
{"name": "Tanglad", "raiting": 4.5, "reviews": 219, "buisness_page": "https://www.yelp.com/biz/tanglad-san-francisco", "Business_website": "https://tangladsf.com"},
{"name": "Dabao Singapore", "raiting": 5.0, "reviews": 73, "buisness_page": "https://www.yelp.com/biz/dabao-singapore-san-francisco", "Business_website": "http://www.dabaosingapore.com"},
{"name": "Farmhouse Kitchen Thai Cuisine", "raiting": 4.0, "reviews": 3435, "buisness_page": "https://www.yelp.com/biz/farmhouse-kitchen-thai-cuisine-san-francisco", "Business_website": "http://www.farmhousethai.com"},
{"name": "Breadbelly", "raiting": 4.5, "reviews": 434, "buisness_page": "https://www.yelp.com/biz/breadbelly-san-francisco", "Business_website": "https://breadbellysf.com"},
{"name": "Lokma", "raiting": 4.5, "reviews": 558, "buisness_page": "https://www.yelp.com/biz/lokma-san-francisco", "Business_website": "http://www.lokmasf.com"},
{"name": "The Italian Homemade Company", "raiting": 4.5, "reviews": 1135, "buisness_page": "https://www.yelp.com/biz/the-italian-homemade-company-san-francisco-6", "Business_website": "http://www.italianhomemadecomp\u2026"},
{"name": "CreoLa", "raiting": 4.5, "reviews": 151, "buisness_page": "https://www.yelp.com/biz/creola-san-francisco-3", "Business_website": "https://www.creolabistro.com"},
{"name": "Beretta", "raiting": 4.5, "reviews": 340, "buisness_page": "https://www.yelp.com/biz/beretta-san-francisco-2", "Business_website": "http://berettasf.com"},
{"name": "Nopa", "raiting": 4.0, "reviews": 5331, "buisness_page": "https://www.yelp.com/biz/nopa-san-francisco", "Business_website": "http://www.nopasf.com"},
{"name": "That's My Jam", "raiting": 5.0, "reviews": 38, "buisness_page": "https://www.yelp.com/biz/thats-my-jam-san-francisco", "Business_website": "http://www.thatsmyjam324.com"},
{"name": "Santeria", "raiting": 4.5, "reviews": 242, "buisness_page": "https://www.yelp.com/biz/santeria-san-francisco", "Business_website": "https://santeria-sf.com"},
{"name": "Alnico", "raiting": 4.5, "reviews": 463, "buisness_page": "https://www.yelp.com/biz/alnico-san-francisco", "Business_website": "https://alnicosf.com"},
{"name": "Vico Cavone", "raiting": 4.0, "reviews": 125, "buisness_page": "https://www.yelp.com/biz/vico-cavone-san-francisco", "Business_website": "http://vicocavone.com"},
{"name": "Horsefeather", "raiting": 4.0, "reviews": 470, "buisness_page": "https://www.yelp.com/biz/horsefeather-san-francisco-2", "Business_website": "http://www.horsefeatherbar.com"},
{"name": "Beit Rima", "raiting": 4.5, "reviews": 611, "buisness_page": "https://www.yelp.com/biz/beit-rima-san-francisco-3", "Business_website": "http://www.beitrimasf.com"},
{"name": "Pizzetta 211", "raiting": 4.5, "reviews": 1424, "buisness_page": "https://www.yelp.com/biz/pizzetta-211-san-francisco", "Business_website": "http://www.pizzetta211.com"},
{"name": "Nopalito", "raiting": 4.0, "reviews": 2001, "buisness_page": "https://www.yelp.com/biz/nopalito-san-francisco", "Business_website": "http://www.nopalitosf.com"},
{"name": "Manna", "raiting": 4.0, "reviews": 1302, "buisness_page": "https://www.yelp.com/biz/manna-san-francisco", "Business_website": "http://www.mannasanfrancisco.c\u2026"},
{"name": "San Tung", "raiting": 4.0, "reviews": 7763, "buisness_page": "https://www.yelp.com/biz/san-tung-san-francisco-2", "Business_website": "https://www.santungsf.com"},
{"name": "Otra", "raiting": 4.5, "reviews": 123, "buisness_page": "https://www.yelp.com/biz/otra-san-francisco-3", "Business_website": "https://www.otrasf.com"},
{"name": "Woodhouse Fish Company", "raiting": 4.0, "reviews": 2484, "buisness_page": "https://www.yelp.com/biz/woodhouse-fish-company-san-francisco-4", "Business_website": "http://woodhousefish.com"},
{"name": "Daeho Kalbijjim & Beef Soup", "raiting": 4.5, "reviews": 1544, "buisness_page": "https://www.yelp.com/biz/daeho-kalbijjim-and-beef-soup-san-francisco-9", "Business_website": "https://daehokalbijjim.com"},
{"name": "Burma Superstar", "raiting": 4.0, "reviews": 7350, "buisness_page": "https://www.yelp.com/biz/burma-superstar-san-francisco-2", "Business_website": "http://www.burmasuperstar.com/"},
{"name": "Ushi Taro Ramen", "raiting": 4.5, "reviews": 435, "buisness_page": "https://www.yelp.com/biz/ushi-taro-ramen-san-francisco-3", "Business_website": "https://ushi-taro-ramen.square\u2026"},
{"name": "Saucy Asian", "raiting": 4.5, "reviews": 411, "buisness_page": "https://www.yelp.com/biz/saucy-asian-san-francisco-2", "Business_website": "https://www.saucyasian.com"},
{"name": "Parada 22", "raiting": 4.0, "reviews": 1393, "buisness_page": "https://www.yelp.com/biz/parada-22-san-francisco", "Business_website": "https://www.paradasf.com"},
{"name": "Arang", "raiting": 4.5, "reviews": 24, "buisness_page": "https://www.yelp.com/biz/arang-san-francisco", "Business_website": "Get Directions"},
{"name": "Dumpling Kitchen", "raiting": 4.0, "reviews": 1973, "buisness_page": "https://www.yelp.com/biz/dumpling-kitchen-san-francisco", "Business_website": "https://dumplingkitchenca.com"},
{"name": "MaMa Ji's", "raiting": 4.0, "reviews": 865, "buisness_page": "https://www.yelp.com/biz/mama-jis-san-francisco-2", "Business_website": "http://www.mamajissf.com"},
{"name": "Sweet Maple", "raiting": 4.5, "reviews": 4488, "buisness_page": "https://www.yelp.com/biz/sweet-maple-san-francisco", "Business_website": "http://www.sweetmaplesf.com"},
{"name": "Souvla", "raiting": 4.0, "reviews": 549, "buisness_page": "https://www.yelp.com/biz/souvla-san-francisco-3", "Business_website": "http://www.souvlasf.com"},
{"name": "Bodega", "raiting": 4.5, "reviews": 243, "buisness_page": "https://www.yelp.com/biz/bodega-san-francisco-3", "Business_website": "http://Bodegarestaurants.com"},
{"name": "Routier", "raiting": 4.5, "reviews": 118, "buisness_page": "https://www.yelp.com/biz/routier-san-francisco", "Business_website": "http://routiersf.com"},
{"name": "Mamahuhu", "raiting": 4.0, "reviews": 290, "buisness_page": "https://www.yelp.com/biz/mamahuhu-san-francisco-2", "Business_website": "https://www.eatmamahuhu.com"},
{"name": "Mangrove Kitchen", "raiting": 4.0, "reviews": 357, "buisness_page": "https://www.yelp.com/biz/mangrove-kitchen-san-francisco", "Business_website": "http://www.mangrovethaikitchen\u2026"},
{"name": "HOT JOHNNIE\u2019S", "raiting": 4.5, "reviews": 346, "buisness_page": "https://www.yelp.com/biz/hot-johnnie-s-san-francisco", "Business_website": "https://hotjohnnies.com"},
{"name": "Rosemary & Pine", "raiting": 4.0, "reviews": 28, "buisness_page": "https://www.yelp.com/biz/rosemary-and-pine-san-francisco", "Business_website": "https://www.rosemaryandpinesf.\u2026"},
{"name": "Cafe Okawari", "raiting": 4.5, "reviews": 259, "buisness_page": "https://www.yelp.com/biz/cafe-okawari-san-francisco", "Business_website": "https://www.cafeokawari.com"},
{"name": "Perilla", "raiting": 4.0, "reviews": 1492, "buisness_page": "https://www.yelp.com/biz/perilla-san-francisco-2", "Business_website": "https://www.irvingperilla.com"},
{"name": "Cafe De Casa", "raiting": 4.5, "reviews": 129, "buisness_page": "https://www.yelp.com/biz/cafe-de-casa-san-francisco-4", "Business_website": "http://www.cafedecasa.com"},
{"name": "California Fish Market Restaurant", "raiting": 4.5, "reviews": 495, "buisness_page": "https://www.yelp.com/biz/california-fish-market-restaurant-san-francisco-3", "Business_website": "http://www.cafishmarketrestaur\u2026"},
{"name": "ILCHA", "raiting": 4.5, "reviews": 117, "buisness_page": "https://www.yelp.com/biz/ilcha-san-francisco", "Business_website": "http://www.ilchasf.com"},
{"name": "Udon Mugizo", "raiting": 4.0, "reviews": 1300, "buisness_page": "https://www.yelp.com/biz/udon-mugizo-san-francisco-11", "Business_website": "http://mugizo-us.com"},
{"name": "Hook Fish", "raiting": 4.5, "reviews": 882, "buisness_page": "https://www.yelp.com/biz/hook-fish-san-francisco-6", "Business_website": "http://www.hookfishco.com"},
{"name": "San Ho Won", "raiting": 4.5, "reviews": 258, "buisness_page": "https://www.yelp.com/biz/san-ho-won-san-francisco-2", "Business_website": "https://sanhowon.com"},
{"name": "Brenda's Meat & Three", "raiting": 4.0, "reviews": 1394, "buisness_page": "https://www.yelp.com/biz/brendas-meat-and-three-san-francisco-3", "Business_website": "http://www.brendasmeatandthree\u2026"},
{"name": "Komaaj", "raiting": 4.5, "reviews": 185, "buisness_page": "https://www.yelp.com/biz/komaaj-san-francisco-5", "Business_website": "http://www.komaaj.com"},
{"name": "Zazie", "raiting": 4.0, "reviews": 4973, "buisness_page": "https://www.yelp.com/biz/zazie-san-francisco", "Business_website": "https://www.zaziesf.com"},
{"name": "Bella Trattoria", "raiting": 4.5, "reviews": 1733, "buisness_page": "https://www.yelp.com/biz/bella-trattoria-san-francisco", "Business_website": "https://osteriabella.com"},
{"name": "NOVY Restaurant", "raiting": 4.0, "reviews": 506, "buisness_page": "https://www.yelp.com/biz/novy-restaurant-san-francisco-6", "Business_website": "http://www.novysf.com"},
{"name": "Billingsgate", "raiting": 4.5, "reviews": 65, "buisness_page": "https://www.yelp.com/biz/billingsgate-san-francisco", "Business_website": "https://www.billingsgatesf.com"},
{"name": "Hinodeya Ramen Bar", "raiting": 4.0, "reviews": 1721, "buisness_page": "https://www.yelp.com/biz/hinodeya-ramen-bar-san-francisco", "Business_website": "http://hinodeyaramen.com"},
{"name": "Cafe R\u00e9veille", "raiting": 4.0, "reviews": 198, "buisness_page": "https://www.yelp.com/biz/cafe-r%C3%A9veille-san-francisco-8", "Business_website": "https://www.cafereveille.com/l\u2026"},
{"name": "Jane on Fillmore", "raiting": 4.0, "reviews": 1121, "buisness_page": "https://www.yelp.com/biz/jane-on-fillmore-san-francisco-2", "Business_website": "http://www.itsjane.com"},
{"name": "Presidio Kebab", "raiting": 4.5, "reviews": 258, "buisness_page": "https://www.yelp.com/biz/presidio-kebab-san-francisco", "Business_website": "http://presidiokebab.com"},
{"name": "The Italian Homemade Company", "raiting": 4.5, "reviews": 1817, "buisness_page": "https://www.yelp.com/biz/the-italian-homemade-company-san-francisco-8", "Business_website": "http://www.italianhomemadecomp\u2026"},
{"name": "Good Good Culture Club", "raiting": 4.5, "reviews": 205, "buisness_page": "https://www.yelp.com/biz/good-good-culture-club-san-francisco", "Business_website": "http://ggccsf.com"},
{"name": "Blind Butcher", "raiting": 4.0, "reviews": 200, "buisness_page": "https://www.yelp.com/biz/blind-butcher-san-francisco-2", "Business_website": "https://blindbutcher.com"},
{"name": "Lavash", "raiting": 4.0, "reviews": 1538, "buisness_page": "https://www.yelp.com/biz/lavash-san-francisco-2", "Business_website": "http://www.lavashsf.com"},
{"name": "Caliente Bistro Kitchen", "raiting": 4.5, "reviews": 150, "buisness_page": "https://www.yelp.com/biz/caliente-bistro-kitchen-san-francisco", "Business_website": "https://calientebistro.com"},
{"name": "Dumpling Baby China Bistro", "raiting": 4.5, "reviews": 166, "buisness_page": "https://www.yelp.com/biz/dumpling-baby-china-bistro-san-francisco-4", "Business_website": "https://dumplingbabysf.com"},
{"name": "Troya", "raiting": 4.0, "reviews": 690, "buisness_page": "https://www.yelp.com/biz/troya-san-francisco-3", "Business_website": "https://www.troyasf.com"},
{"name": "Ragazza", "raiting": 4.0, "reviews": 732, "buisness_page": "https://www.yelp.com/biz/ragazza-san-francisco", "Business_website": "http://www.ragazzasf.com"},
{"name": "Frances", "raiting": 4.5, "reviews": 1536, "buisness_page": "https://www.yelp.com/biz/frances-san-francisco", "Business_website": "http://www.frances-sf.com/"},
{"name": "Cha Cha Cha", "raiting": 4.0, "reviews": 3391, "buisness_page": "https://www.yelp.com/biz/cha-cha-cha-san-francisco-4", "Business_website": "http://www.chachachasf.com"},
{"name": "Bansang", "raiting": 4.0, "reviews": 140, "buisness_page": "https://www.yelp.com/biz/bansang-san-francisco-3", "Business_website": "https://www.bansangsf.com"},
{"name": "The Public Izakaya", "raiting": 4.5, "reviews": 143, "buisness_page": "https://www.yelp.com/biz/the-public-izakaya-san-francisco", "Business_website": "Get Directions"},
{"name": "Anchor Oyster Bar", "raiting": 4.5, "reviews": 1615, "buisness_page": "https://www.yelp.com/biz/anchor-oyster-bar-san-francisco", "Business_website": "http://www.anchoroysterbar.com"},
{"name": "Surisan", "raiting": 4.5, "reviews": 2965, "buisness_page": "https://www.yelp.com/biz/surisan-san-francisco", "Business_website": "https://www.surisansf.com"},
{"name": "L\u2019Ardoise Bistro", "raiting": 4.5, "reviews": 1374, "buisness_page": "https://www.yelp.com/biz/l-ardoise-bistro-san-francisco", "Business_website": "http://www.ardoisesf.com"},
{"name": "Unco Frank\u2019s", "raiting": 4.5, "reviews": 71, "buisness_page": "https://www.yelp.com/biz/unco-frank-s-san-francisco", "Business_website": "Get Directions"},
{"name": "Lark", "raiting": 4.0, "reviews": 316, "buisness_page": "https://www.yelp.com/biz/lark-san-francisco-2", "Business_website": "http://www.larksf.com/"},
{"name": "Ben Thai Cafe", "raiting": 4.5, "reviews": 783, "buisness_page": "https://www.yelp.com/biz/ben-thai-cafe-san-francisco", "Business_website": "http://benthaicafe.com"},
{"name": "Mezze and Mooore", "raiting": 5.0, "reviews": 61, "buisness_page": "https://www.yelp.com/biz/mezze-and-mooore-san-francisco-2", "Business_website": "Get Directions"},
{"name": "Freekeh", "raiting": 4.5, "reviews": 101, "buisness_page": "https://www.yelp.com/biz/freekeh-san-francisco", "Business_website": "http://freekehsf.com"},
{"name": "Kaiju Eats Ramen and Izakaya", "raiting": 4.0, "reviews": 880, "buisness_page": "https://www.yelp.com/biz/kaiju-eats-ramen-and-izakaya-san-francisco-3", "Business_website": "https://www.kaijueatsramenizak\u2026"},
{"name": "Tratto", "raiting": 4.0, "reviews": 639, "buisness_page": "https://www.yelp.com/biz/tratto-san-francisco", "Business_website": "http://tratto-sf.com"},
{"name": "Che Fico Alimentari", "raiting": 4.0, "reviews": 154, "buisness_page": "https://www.yelp.com/biz/che-fico-alimentari-san-francisco", "Business_website": "https://www.cheficoalimentari.\u2026"},
{"name": "State Bird Provisions", "raiting": 4.0, "reviews": 3024, "buisness_page": "https://www.yelp.com/biz/state-bird-provisions-san-francisco", "Business_website": "https://statebirdsf.com/home/"},
{"name": "Mamanoko", "raiting": 4.5, "reviews": 462, "buisness_page": "https://www.yelp.com/biz/mamanoko-san-francisco-2", "Business_website": "http://www.mamanokosf.com"},
{"name": "Birch & Rye", "raiting": 4.0, "reviews": 87, "buisness_page": "https://www.yelp.com/biz/birch-and-rye-san-francisco-2", "Business_website": "https://birchandryesf.com"},
{"name": "Cote Ouest Bistro", "raiting": 4.5, "reviews": 135, "buisness_page": "https://www.yelp.com/biz/cote-ouest-bistro-san-francisco", "Business_website": "https://www.coteouestbistro.co\u2026"},
{"name": "DragonEats", "raiting": 4.5, "reviews": 283, "buisness_page": "https://www.yelp.com/biz/dragoneats-san-francisco-7", "Business_website": "https://dragoneats.com"},
{"name": "Kokkari Estiatorio", "raiting": 4.5, "reviews": 4986, "buisness_page": "https://www.yelp.com/biz/kokkari-estiatorio-san-francisco", "Business_website": "http://www.kokkari.com"},
{"name": "LaLe", "raiting": 4.0, "reviews": 568, "buisness_page": "https://www.yelp.com/biz/lale-san-francisco-2", "Business_website": "http://www.lalesf.com"},
{"name": "Mersea", "raiting": 4.5, "reviews": 1040, "buisness_page": "https://www.yelp.com/biz/mersea-san-francisco-4", "Business_website": "http://www.mersea.restaurant"},
{"name": "Malasa", "raiting": 4.5, "reviews": 177, "buisness_page": "https://www.yelp.com/biz/malasa-san-francisco", "Business_website": "http://www.malasasf.com"},
{"name": "The Little Chihuahua", "raiting": 4.0, "reviews": 1569, "buisness_page": "https://www.yelp.com/biz/the-little-chihuahua-san-francisco", "Business_website": "http://thelittlechihuahua.com"},
{"name": "Heroic Italian", "raiting": 4.5, "reviews": 98, "buisness_page": "https://www.yelp.com/biz/heroic-italian-san-francisco-2", "Business_website": "https://heroicitalian.com"},
{"name": "Dinosaurs", "raiting": 4.0, "reviews": 958, "buisness_page": "https://www.yelp.com/biz/dinosaurs-san-francisco-4", "Business_website": "http://eatdinosaurs.com"},
{"name": "Eats", "raiting": 4.0, "reviews": 1300, "buisness_page": "https://www.yelp.com/biz/eats-san-francisco", "Business_website": "https://www.eatsrestaurantsf.c\u2026"},
{"name": "Amitis Caf\u00e9", "raiting": 4.5, "reviews": 218, "buisness_page": "https://www.yelp.com/biz/amitis-caf%C3%A9-san-francisco-2", "Business_website": "Get Directions"},
{"name": "MaMo", "raiting": 4.5, "reviews": 194, "buisness_page": "https://www.yelp.com/biz/mamo-san-francisco", "Business_website": "http://mamosf.com"},
{"name": "Breakfast at Tiffany's", "raiting": 4.0, "reviews": 1071, "buisness_page": "https://www.yelp.com/biz/breakfast-at-tiffanys-san-francisco", "Business_website": "http://breakfastattiffanyssf.c\u2026"},
{"name": "Hazie's", "raiting": 4.0, "reviews": 66, "buisness_page": "https://www.yelp.com/biz/hazies-san-francisco", "Business_website": "https://www.haziessf.com"},
{"name": "Bacco", "raiting": 4.0, "reviews": 538, "buisness_page": "https://www.yelp.com/biz/bacco-san-francisco", "Business_website": "http://www.baccosf.com"},
{"name": "Delarosa", "raiting": 4.0, "reviews": 1813, "buisness_page": "https://www.yelp.com/biz/delarosa-san-francisco", "Business_website": "http://www.delarosasf.com"},
{"name": "opa cafe", "raiting": 4.5, "reviews": 462, "buisness_page": "https://www.yelp.com/biz/opa-cafe-san-francisco", "Business_website": "https://www.opasf.com"},
{"name": "Moku Yakitori-Ya", "raiting": 4.5, "reviews": 63, "buisness_page": "https://www.yelp.com/biz/moku-yakitori-ya-san-francisco", "Business_website": "Get Directions"},
{"name": "Q's Sandwich Shop", "raiting": 4.5, "reviews": 31, "buisness_page": "https://www.yelp.com/biz/qs-sandwich-shop-san-francisco", "Business_website": "https://qs-sandwich-shop.squar\u2026"},
{"name": "Cracked & Battered - Marina", "raiting": 4.5, "reviews": 388, "buisness_page": "https://www.yelp.com/biz/cracked-and-battered-marina-san-francisco", "Business_website": "http://www.crackedandbattered.\u2026"},
{"name": "Hoshinoya", "raiting": 4.5, "reviews": 199, "buisness_page": "https://www.yelp.com/biz/hoshinoya-san-francisco", "Business_website": "http://www.hoshinoyasf.com"},
{"name": "Jaranita", "raiting": 4.0, "reviews": 382, "buisness_page": "https://www.yelp.com/biz/jaranita-san-francisco-4", "Business_website": "http://www.jaranitasf.com"},
{"name": "Poesia", "raiting": 4.0, "reviews": 866, "buisness_page": "https://www.yelp.com/biz/poesia-san-francisco", "Business_website": "http://poesiasf.com/"},
{"name": "Mr. Digby's Bar & Restaurant", "raiting": 4.0, "reviews": 124, "buisness_page": "https://www.yelp.com/biz/mr-digbys-bar-and-restaurant-san-francisco", "Business_website": "http://www.mrdigbys.com"},
{"name": "Roma Antica", "raiting": 4.5, "reviews": 1145, "buisness_page": "https://www.yelp.com/biz/roma-antica-san-francisco-3", "Business_website": "https://www.romaSF.com"},
{"name": "Castro Tarts", "raiting": 4.0, "reviews": 316, "buisness_page": "https://www.yelp.com/biz/castro-tarts-san-francisco-2", "Business_website": "https://castrotarts.squarespac\u2026"},
{"name": "Shanghai Dumpling King", "raiting": 4.5, "reviews": 59, "buisness_page": "https://www.yelp.com/biz/shanghai-dumpling-king-san-francisco-4", "Business_website": "https://dumplingrestaurantsanf\u2026"},
{"name": "Noodle in a Haystack", "raiting": 5.0, "reviews": 57, "buisness_page": "https://www.yelp.com/biz/noodle-in-a-haystack-san-francisco", "Business_website": "http://www.noodleinhaystack.co\u2026"},
{"name": "Taishoken San Francisco", "raiting": 4.5, "reviews": 96, "buisness_page": "https://www.yelp.com/biz/taishoken-san-francisco-san-francisco", "Business_website": "https://www.taishokenusa.com"},
{"name": "Izakaya Sozai", "raiting": 4.0, "reviews": 2153, "buisness_page": "https://www.yelp.com/biz/izakaya-sozai-san-francisco", "Business_website": "http://www.izakayasozai.com/"},
{"name": "Taksim", "raiting": 4.5, "reviews": 64, "buisness_page": "https://www.yelp.com/biz/taksim-san-francisco", "Business_website": "http://www.taksimsf.com"},
{"name": "1428 HAIGHT Patio Cafe & Crepery", "raiting": 4.0, "reviews": 461, "buisness_page": "https://www.yelp.com/biz/1428-haight-patio-cafe-and-crepery-san-francisco", "Business_website": "http://www.1428haight.com"},
{"name": "Outerlands", "raiting": 4.0, "reviews": 2349, "buisness_page": "https://www.yelp.com/biz/outerlands-san-francisco", "Business_website": "http://outerlandssf.com"},
{"name": "The View Lounge", "raiting": 4.0, "reviews": 1917, "buisness_page": "https://www.yelp.com/biz/the-view-lounge-san-francisco", "Business_website": "https://www.marriott.com/hotel\u2026"},
{"name": "Hodala", "raiting": 4.0, "reviews": 659, "buisness_page": "https://www.yelp.com/biz/hodala-san-francisco", "Business_website": "Get Directions"},
{"name": "Diamond Cafe", "raiting": 4.5, "reviews": 169, "buisness_page": "https://www.yelp.com/biz/diamond-cafe-san-francisco", "Business_website": "Get Directions"},
{"name": "Suppenk\u00fcche", "raiting": 4.0, "reviews": 3297, "buisness_page": "https://www.yelp.com/biz/suppenk%C3%BCche-san-francisco-2", "Business_website": "http://www.suppenkuche.com"},
{"name": "Nara Restaurant & Sake Bar", "raiting": 4.5, "reviews": 1863, "buisness_page": "https://www.yelp.com/biz/nara-restaurant-and-sake-bar-san-francisco", "Business_website": "Get Directions"},
{"name": "Vive La Tarte", "raiting": 4.5, "reviews": 111, "buisness_page": "https://www.yelp.com/biz/vive-la-tarte-san-francisco-5", "Business_website": "http://www.vivelatarte.com"},
{"name": "Spork Restaurant", "raiting": 5.0, "reviews": 134, "buisness_page": "https://www.yelp.com/biz/spork-restaurant-san-francisco-3", "Business_website": "http://www.sfspork.com"},
{"name": "Wicked 6 Bar & Bites", "raiting": 5.0, "reviews": 12, "buisness_page": "https://www.yelp.com/biz/wicked-6-bar-and-bites-san-francisco-2", "Business_website": "http://www.wicked6bar.com"},
{"name": "Souvla", "raiting": 4.0, "reviews": 1641, "buisness_page": "https://www.yelp.com/biz/souvla-san-francisco", "Business_website": "http://www.souvla.com"},
{"name": "Yuanbao Jiaozi", "raiting": 4.5, "reviews": 500, "buisness_page": "https://www.yelp.com/biz/yuanbao-jiaozi-san-francisco-2", "Business_website": "https://yuanbaojiaozisf.com"},
{"name": "Flores", "raiting": 4.0, "reviews": 883, "buisness_page": "https://www.yelp.com/biz/flores-san-francisco", "Business_website": "https://www.floressf.com"},
{"name": "Om Sabor", "raiting": 4.5, "reviews": 39, "buisness_page": "https://www.yelp.com/biz/om-sabor-san-francisco-2", "Business_website": "https://omsabor.com"},
{"name": "Chome", "raiting": 4.5, "reviews": 204, "buisness_page": "https://www.yelp.com/biz/chome-san-francisco-3", "Business_website": "Get Directions"},
{"name": "Kui Shin Bo", "raiting": 4.0, "reviews": 899, "buisness_page": "https://www.yelp.com/biz/kui-shin-bo-san-francisco-2", "Business_website": "http://www.kuishinborestaurant\u2026"},
{"name": "Ocean Indian Cuisine", "raiting": 5.0, "reviews": 281, "buisness_page": "https://www.yelp.com/biz/ocean-indian-cuisine-san-francisco", "Business_website": "http://www.oceanindiancuisine.\u2026"},
{"name": "Sorella", "raiting": 4.5, "reviews": 103, "buisness_page": "https://www.yelp.com/biz/sorella-san-francisco", "Business_website": "http://www.sorellasf.com"},
{"name": "The Pawn Shop", "raiting": 4.5, "reviews": 496, "buisness_page": "https://www.yelp.com/biz/the-pawn-shop-san-francisco", "Business_website": "https://thepawnshopsf.com"},
{"name": "Besharam", "raiting": 4.0, "reviews": 376, "buisness_page": "https://www.yelp.com/biz/besharam-san-francisco", "Business_website": "https://www.besharamrestaurant\u2026"}
]